{
  "type": "minecraft:block",
  "pools": [
    {
      "rolls": 1,
      "entries": [
        {
          "type": "minecraft:item",
          "functions": [
            {
              "function": "minecraft:copy_name",
              "source": "block_entity"
            },
            {
              "function": "minecraft:copy_nbt",
              "source": "block_entity",
              "ops": [
                {
                  "source": "inv",
                  "target": "BlockEntityTag.inv",
                  "op": "replace"
                },
                {
                  "source": "mana",
                  "target": "BlockEntityTag.mana",
                  "op": "replace"
                },
                {
                  "source": "progress",
                  "target": "BlockEntityTag.progress",
                  "op": "replace"
                }
              ]
            }
          ],
          "name": "botanicalmachinery:alfheim_market"
        }
      ],
      "conditions": [
        {
          "condition": "minecraft:survives_explosion"
        }
      ]
    }
  ]
}